{"cameraMode":{"drawMode":0,"name":"Shaded","section":"Shading Mode"},"sceneLighting":true,"audioPlay":false,"sceneViewState":{"m_AlwaysRefresh":false,"showFog":true,"showSkybox":true,"showFlares":true,"showImageEffects":true,"showParticleSystems":true,"showVisualEffectGraphs":true,"m_FxEnabled":true},"in2DMode":false,"pivot":{"x":1.125,"y":0.379000186920166,"z":2.513000249862671},"rotation":{"x":0.09509027749300003,"y":0.3629637062549591,"z":-0.03726457431912422,"w":0.9261913895606995},"size":0.8660253882408142,"orthographic":true}